davtelepot/__init__.py
davtelepot/__main__.py
davtelepot/administration_tools.py
davtelepot/api.py
davtelepot/api_helper.py
davtelepot/authorization.py
davtelepot/bot.py
davtelepot/cli.py
davtelepot/database.py
davtelepot/helper.py
davtelepot/ietf_language_tags.csv
davtelepot/languages.py
davtelepot/messages.py
davtelepot/suggestions.py
davtelepot/useful_tools.py
davtelepot/utilities.py
davtelepot/data/__init__.py
davtelepot/tools/__init__.py
davtelepot/tools/merge_files.py
examples/__init__.py
examples/a_simple_bot.py
examples/more_bots_together.py
examples/webhook_powered_bot.py
davtelepot-2.10.10.dist-info/LICENSE
davtelepot-2.10.10.dist-info/METADATA
davtelepot-2.10.10.dist-info/WHEEL
davtelepot-2.10.10.dist-info/top_level.txt
davtelepot-2.10.10.dist-info/RECORD
