Metadata-Version: 2.2
Name: davtelepot
Version: 2.10.10
Summary: Telegram bot API mirroring class, featuring dataset-powered SQLite databases.
Home-page: https://gitea.davte.it/davte/davtelepot
Author: Davide Testa
Author-email: davide@davte.it
License: GNU General Public License v3.0
Keywords: telegram bot python asyncio async aiohttp
Platform: any
Classifier: Development Status :: 5 - Production/Stable
Classifier: Environment :: Console
Classifier: Framework :: AsyncIO
Classifier: Intended Audience :: Developers
Classifier: License :: OSI Approved :: GNU General Public License v3 (GPLv3)
Classifier: Natural Language :: English
Classifier: Operating System :: OS Independent
Classifier: Programming Language :: Python :: 3 :: Only
Classifier: Topic :: Communications :: Chat
Requires-Python: >=3.5
License-File: LICENSE
Requires-Dist: aiohttp
Requires-Dist: bs4
Requires-Dist: dataset
Dynamic: author
Dynamic: author-email
Dynamic: classifier
Dynamic: description
Dynamic: description-content-type
Dynamic: home-page
Dynamic: keywords
Dynamic: license
Dynamic: platform
Dynamic: requires-dist
Dynamic: requires-python
Dynamic: summary
